[
    {
        "iconUrl": "https://www.google.com/s2/favicons?domain=animehay.in&sz=%size%",
        "apiVersion": 1,
        "repositoryUrl": "https://codeberg.org/tearrs/cloudstream-vietnamese",
        "fileSize": 11361,
        "status": 1,
        "language": "vi",
        "authors": [
            "anhdadendaden"
        ],
        "tvTypes": [
            "Anime"
        ],
        "version": 1,
        "internalName": "AnimeHayProvider",
        "url": "https://codeberg.org/tearrs/cloudstream-vietnamese/raw/branch/main/AnimeHayProvider.cs3",
        "name": "AnimeHayProvider"
    },
    {
        "iconUrl": "https://www.google.com/s2/favicons?domain=bluphim.art&sz=%size%",
        "apiVersion": 1,
        "repositoryUrl": "https://codeberg.org/tearrs/cloudstream-vietnamese",
        "fileSize": 15616,
        "status": 1,
        "language": "vi",
        "authors": [
            "anhdadendaden"
        ],
        "tvTypes": [
            "AsianDrama",
            "Anime",
            "TvSeries",
            "Movie"
        ],
        "version": 1,
        "internalName": "BluphimProvider",
        "url": "https://codeberg.org/tearrs/cloudstream-vietnamese/raw/branch/main/BluphimProvider.cs3",
        "name": "BluphimProvider"
    },
    {
        "iconUrl": "https://www.google.com/s2/favicons?domain=hhpanda.tube&sz=%size%",
        "apiVersion": 1,
        "repositoryUrl": "https://codeberg.org/tearrs/cloudstream-vietnamese",
        "fileSize": 13485,
        "status": 1,
        "language": "vi",
        "authors": [
            "anhdadendaden"
        ],
        "tvTypes": [
            "Anime"
        ],
        "version": 2,
        "internalName": "HHPandaProvider",
        "url": "https://codeberg.org/tearrs/cloudstream-vietnamese/raw/branch/main/HHPandaProvider.cs3",
        "name": "HHPandaProvider"
    },
    {
        "iconUrl": "https://kkphim.vip/template/kkphim/static/img/favicon.png",
        "apiVersion": 1,
        "repositoryUrl": "https://codeberg.org/tearrs/cloudstream-vietnamese",
        "fileSize": 15038,
        "status": 1,
        "language": "vi",
        "authors": [
            "anhdadendaden"
        ],
        "tvTypes": [
            "AsianDrama",
            "Anime",
            "TvSeries",
            "Movie"
        ],
        "version": 2,
        "internalName": "KKPhimProvider",
        "url": "https://codeberg.org/tearrs/cloudstream-vietnamese/raw/branch/main/KKPhimProvider.cs3",
        "name": "KKPhimProvider"
    },
    {
        "iconUrl": "https://www.google.com/s2/favicons?domain=motchilltv.us&sz=%size%",
        "apiVersion": 1,
        "repositoryUrl": "https://codeberg.org/tearrs/cloudstream-vietnamese",
        "fileSize": 14052,
        "status": 0,
        "language": "vi",
        "authors": [
            "anhdadendaden"
        ],
        "tvTypes": [
            "AsianDrama",
            "Anime",
            "TvSeries",
            "Movie"
        ],
        "version": 2,
        "internalName": "MotchillProvider",
        "url": "https://codeberg.org/tearrs/cloudstream-vietnamese/raw/branch/main/MotchillProvider.cs3",
        "name": "MotchillProvider"
    },
    {
        "iconUrl": "https://phim.nguonc.com/public/images/Logo/tv.png",
        "apiVersion": 1,
        "repositoryUrl": "https://codeberg.org/tearrs/cloudstream-vietnamese",
        "fileSize": 14827,
        "status": 1,
        "language": "vi",
        "authors": [
            "anhdadendaden"
        ],
        "tvTypes": [
            "AsianDrama",
            "Anime",
            "TvSeries",
            "Movie"
        ],
        "version": 3,
        "internalName": "NguonCProvider",
        "url": "https://codeberg.org/tearrs/cloudstream-vietnamese/raw/branch/main/NguonCProvider.cs3",
        "name": "NguonCProvider"
    },
    {
        "iconUrl": "https://ophim16.cc/icon_ophim.png",
        "apiVersion": 1,
        "repositoryUrl": "https://codeberg.org/tearrs/cloudstream-vietnamese",
        "fileSize": 15081,
        "status": 1,
        "language": "vi",
        "authors": [
            "anhdadendaden"
        ],
        "tvTypes": [
            "AsianDrama",
            "Anime",
            "TvSeries",
            "Movie"
        ],
        "version": 5,
        "internalName": "OPhimProvider",
        "url": "https://codeberg.org/tearrs/cloudstream-vietnamese/raw/branch/main/OPhimProvider.cs3",
        "name": "OPhimProvider"
    },
    {
        "iconUrl": "https://www.google.com/s2/favicons?domain=phimlongtieng.com&sz=%size%",
        "apiVersion": 1,
        "repositoryUrl": "https://codeberg.org/tearrs/cloudstream-vietnamese",
        "fileSize": 15051,
        "status": 1,
        "language": "vi",
        "authors": [
            "anhdadendaden"
        ],
        "tvTypes": [
            "AsianDrama",
            "Anime",
            "TvSeries",
            "Movie"
        ],
        "version": 1,
        "internalName": "PhimLongTiengProvider",
        "url": "https://codeberg.org/tearrs/cloudstream-vietnamese/raw/branch/main/PhimLongTiengProvider.cs3",
        "name": "PhimLongTiengProvider"
    },
    {
        "iconUrl": "https://www.google.com/s2/favicons?domain=phimmoichillk.net&sz=%size%",
        "apiVersion": 1,
        "repositoryUrl": "https://codeberg.org/tearrs/cloudstream-vietnamese",
        "fileSize": 15054,
        "status": 1,
        "language": "vi",
        "authors": [
            "anhdadendaden"
        ],
        "tvTypes": [
            "AsianDrama",
            "Anime",
            "TvSeries",
            "Movie"
        ],
        "version": 1,
        "internalName": "PhimmoichillProvider",
        "url": "https://codeberg.org/tearrs/cloudstream-vietnamese/raw/branch/main/PhimmoichillProvider.cs3",
        "name": "PhimmoichillProvider"
    },
    {
        "iconUrl": "https://www.google.com/s2/favicons?domain=subnhanh.li&sz=%size%",
        "apiVersion": 1,
        "repositoryUrl": "https://codeberg.org/tearrs/cloudstream-vietnamese",
        "fileSize": 12275,
        "status": 1,
        "language": "vi",
        "authors": [
            "anhdadendaden"
        ],
        "tvTypes": [
            "AsianDrama",
            "Anime",
            "TvSeries",
            "Movie"
        ],
        "version": 2,
        "internalName": "SubnhanhProvider",
        "url": "https://codeberg.org/tearrs/cloudstream-vietnamese/raw/branch/main/SubnhanhProvider.cs3",
        "name": "SubnhanhProvider"
    }
]
